{
    "total":8,
     "data":[
         {
             "imgUrl":"https://ss0.bdstatic.com/70cFvHSh_Q1YnxGkpoWK1HF6hhy/it/u=1083599257,3933212247&fm=26&gp=0.jpg",
             "SingerName":"摩登兄弟"
         },
         {
             "imgUrl":"https://ss0.bdstatic.com/70cFuHSh_Q1YnxGkpoWK1HF6hhy/it/u=3549451235,1307751507&fm=26&gp=0.jpg",
             "SingerName":"周杰伦"
         },
         {
             "imgUrl":"https://ss0.bdstatic.com/70cFuHSh_Q1YnxGkpoWK1HF6hhy/it/u=3549451235,1307751507&fm=26&gp=0.jpg",
             "SingerName":"薛之谦"
         },
         {
             "imgUrl":"https://ss0.bdstatic.com/70cFuHSh_Q1YnxGkpoWK1HF6hhy/it/u=3549451235,1307751507&fm=26&gp=0.jpg",
             "SingerName":"TFBOYS"
         },
         {
             "imgUrl":"https://ss0.bdstatic.com/70cFuHSh_Q1YnxGkpoWK1HF6hhy/it/u=3549451235,1307751507&fm=26&gp=0.jpg",
             "SingerName":"张杰"
         },
         {
             "imgUrl":"https://ss0.bdstatic.com/70cFuHSh_Q1YnxGkpoWK1HF6hhy/it/u=3549451235,1307751507&fm=26&gp=0.jpg",
             "SingerName":"王力宏"
         },
         {
             "imgUrl":"https://ss0.bdstatic.com/70cFuHSh_Q1YnxGkpoWK1HF6hhy/it/u=3549451235,1307751507&fm=26&gp=0.jpg",
             "SingerName":"林俊杰"
         },
         {
             "imgUrl":"https://ss0.bdstatic.com/70cFuHSh_Q1YnxGkpoWK1HF6hhy/it/u=3549451235,1307751507&fm=26&gp=0.jpg",
             "SingerName":"臭不要脸"
         }
     ]
}